pie/__init__.py
pie/__main__.py
pie/pie.py
pie/assets/{{page}}.md
pie/assets/{{website_name}}/index.html
pie/assets/{{website_name}}/page_first.md
pie/assets/{{website_name}}/page_main.md
pie/assets/{{website_name}}/page_second.md
pie/assets/{{website_name}}/page_third.md
pie/assets/{{website_name}}/styles.css
pie/assets/{{website_name}}/styles.rtl.css
pie/assets/{{website_name}}/{{website_name}}.yaml
pie/assets/{{website_name}}/assets/highlight.min.js
pie/assets/{{website_name}}/assets/zenburn.min.css
pie/assets/{{website_name}}/assets/brand/bootstrap-logo-white.svg
pie/assets/{{website_name}}/assets/brand/bootstrap-logo.svg
pie/assets/{{website_name}}/assets/dist/css/bootstrap.min.css
pie/assets/{{website_name}}/assets/dist/css/bootstrap.min.css.map
pie/assets/{{website_name}}/assets/dist/css/bootstrap.rtl.min.css
pie/assets/{{website_name}}/assets/dist/css/bootstrap.rtl.min.css.map
pie/assets/{{website_name}}/assets/dist/js/bootstrap.bundle.min.js
pie/assets/{{website_name}}/assets/dist/js/bootstrap.bundle.min.js.map
pie/core/__init__.py
pie/core/extension.py
pie/core/generator copy 2.py
pie/core/generator copy.py
pie/core/generator.py
pie/core/generator_bak.py
pie/core/server.py
pie/core/utils.py
pie/extensions/__init__.py
pie/extensions/menu/__init__.py
pie/extensions/menu/menu.py
pie/extensions/mostrecent/__init__.py
pie/extensions/mostrecent/mostrecent.py
pie/extensions/pagelist/__init__.py
pie/extensions/pagelist/pagelist.py
pie/extensions/search/__init__.py
pie/extensions/search/search.py
pie/extensions/tags/__init__.py
pie/extensions/tags/default_conf.py
pie/extensions/tags/tags.py
staticpie-0.5.0.dist-info/LICENSE
staticpie-0.5.0.dist-info/METADATA
staticpie-0.5.0.dist-info/WHEEL
staticpie-0.5.0.dist-info/entry_points.txt
staticpie-0.5.0.dist-info/top_level.txt
staticpie-0.5.0.dist-info/RECORD
