Metadata-Version: 2.1
Name: staticpie
Version: 0.5.0
Summary: Simple and extensible static site generator written in Python.
Home-page: https://github.com/rsusik/staticpie
Author: Robert Susik
Author-email: robert.susik@gmail.com
License: GPLv3
Platform: UNKNOWN
Classifier: Topic :: Utilities
Classifier: Environment :: Console
Classifier: Intended Audience :: Developers
Classifier: Programming Language :: Python
Classifier: Topic :: Internet :: WWW/HTTP
Classifier: Topic :: Software Development :: Code Generators
Classifier: Topic :: Text Processing :: Markup :: Markdown
Classifier: Topic :: Text Processing :: Markup :: HTML
Requires-Python: >=3.8
Requires-Dist: PyYaml
Requires-Dist: Jinja2 (>=2)
Requires-Dist: Markdown (>=3)
Requires-Dist: psutil (>=5)
Requires-Dist: lxml (>=4)
Requires-Dist: websockets (>=9)
Requires-Dist: watchdog (>=2)
Requires-Dist: pymdown-extensions (>=8)
Requires-Dist: rich (>=10)
Requires-Dist: ncache
